shipyard_notion/__init__.py
shipyard_notion/cli/authtest.py
shipyard_notion/cli/download.py
shipyard_notion/cli/upload.py
shipyard_notion/notion.py
shipyard_notion/notion_utils.py
shipyard_notion-0.1.1.dist-info/METADATA
shipyard_notion-0.1.1.dist-info/WHEEL
shipyard_notion-0.1.1.dist-info/RECORD
