Metadata-Version: 2.1
Name: shipyard-notion
Version: 0.1.1
Summary: 
License: Apache 2.0
Author: wrp801
Author-email: wespoulsen@gmail.com
Requires-Python: >=3.9,<4.0
Classifier: License :: Other/Proprietary License
Classifier: Programming Language :: Python :: 3
Classifier: Programming Language :: Python :: 3.9
Classifier: Programming Language :: Python :: 3.10
Classifier: Programming Language :: Python :: 3.11
Requires-Dist: notion-client (>=2.0.0,<3.0.0)
Requires-Dist: pandas (==1.5.3)
Requires-Dist: requests (==2.31)
Requires-Dist: shipyard-templates (==0.4.1)
